LoadingWindow/LoadingWindow.py
LoadingWindow/Threading.py
LoadingWindow/__init__.py
LoadingWindow/__main__.py
LoadingWindow-3.1.2.dist-info/LICENSE
LoadingWindow-3.1.2.dist-info/METADATA
LoadingWindow-3.1.2.dist-info/WHEEL
LoadingWindow-3.1.2.dist-info/top_level.txt
LoadingWindow-3.1.2.dist-info/RECORD
