Metadata-Version: 2.1
Name: LoadingWindow
Version: 3.1.2
Summary: An easy to use LoadingWindow for Apps that needs pre-setups
Home-page: https://github.com/LeeFuuChang/PyPi-LoadingWindow
Author: LeeFuuChang
Author-email: a0962014248gg@gmail.com
License: MIT
Project-URL: Source, https://github.com/LeeFuuChang/PyPi-LoadingWindow
Project-URL: Tracker, https://github.com/LeeFuuChang/PyPi-LoadingWindow/issues
Keywords: python,python3,PyQt5,Loading Window
Platform: UNKNOWN
Classifier: Development Status :: 5 - Production/Stable
Classifier: Intended Audience :: Developers
Classifier: Programming Language :: Python :: 3 :: Only
Classifier: Programming Language :: Python :: 3.6
Classifier: Programming Language :: Python :: 3.7
Classifier: Programming Language :: Python :: 3.8
Classifier: Programming Language :: Python :: 3.9
Classifier: Programming Language :: Python :: 3.10
Classifier: Programming Language :: Python :: 3.11
Classifier: Programming Language :: Python :: 3.12
Classifier: Operating System :: Unix
Classifier: Operating System :: MacOS :: MacOS X
Classifier: Operating System :: Microsoft :: Windows
Requires-Dist: PyQt5
